LICENSE
README.md
setup.py
PyQuantKit/_FinanceDecimal.py
PyQuantKit/__init__.py
PyQuantKit/console_utils.py
PyQuantKit/market_utils.py
PyQuantKit/technical_analysis.py
PyQuantKit/trade_utils.py
PyQuantKit.egg-info/PKG-INFO
PyQuantKit.egg-info/SOURCES.txt
PyQuantKit.egg-info/dependency_links.txt
PyQuantKit.egg-info/requires.txt
PyQuantKit.egg-info/top_level.txt