Metadata-Version: 2.1
Name: PyQuantKit
Version: 0.3.1
Summary: Python Toolkit for Quantitative Finance
Home-page: https://github.com/BolunHan/PyQuantKit.git
Author: Bolun.Han
Author-email: Bolun.Han@outlook.com
License: MIT
Classifier: Programming Language :: Python :: 3.8
Classifier: Programming Language :: Python :: 3.9
Classifier: Programming Language :: Python :: 3.10
Classifier: Operating System :: OS Independent
Requires-Python: >=3.8
License-File: LICENSE
Requires-Dist: numpy
Requires-Dist: pandas
